twock/__init__.py
twock/twock.py
twock-0.1.2.dist-info/entry_points.txt
twock-0.1.2.dist-info/LICENSE
twock-0.1.2.dist-info/WHEEL
twock-0.1.2.dist-info/METADATA
twock-0.1.2.dist-info/RECORD
