Metadata-Version: 2.1
Name: twock
Version: 0.1.2
Summary: Ping/Knock a list of tweets to enquire their status (deleted/available/...) #twockknock
Home-page: https://github.com/Leibniz-HBI/twock
License: MIT
Author: Felix Victor Münch
Author-email: f.muench@leibniz-hbi.de
Requires-Python: >=3.8,<4.0
Classifier: Development Status :: 3 - Alpha
Classifier: Environment :: Console
Classifier: Intended Audience :: Science/Research
Classifier: License :: OSI Approved :: MIT License
Classifier: Programming Language :: Python :: 3
Classifier: Programming Language :: Python :: 3.8
Classifier: Programming Language :: Python :: 3.9
Requires-Dist: PyYAML (>=5.4.1,<6.0.0)
Requires-Dist: click (>=8.0.1,<9.0.0)
Requires-Dist: loguru (>=0.5.3,<0.6.0)
Requires-Dist: ndjson (>=0.3.1,<0.4.0)
Requires-Dist: pandas (>=1.3.1,<2.0.0)
Requires-Dist: twarc (>=2.3.10,<3.0.0)
Project-URL: Repository, https://github.com/Leibniz-HBI/twock
